<comp_cd>
  1022
  <identifier>
    <identifier>10128_00_m_11.jpg</identifier>
    <copyright>LOTTE Data Communication Company</copyright>
  </identifier>
  <div_cd>
    09
    <item_cd>10220900012</item_cd>
    <item_no>10128</item_no>
    <div_l>음료</div_l>
    <div_m>과채음료</div_m>
    <div_s>채소음료</div_s>
    <div_n>채소음료</div_n>
    <comp_nm>웅진식품</comp_nm>
    <img_prod_nm>웅진자연은토마토500ML</img_prod_nm>
    <volume>500ML</volume>
    <barcd>8801382130314</barcd>
    <width>6</width>
    <length>6</length>
    <height>21</height>
    <nutrition_info>{"1회제공량":"","총내용량(g)":"","총내용량(mL)":"500","에너지(㎉)":"215","단백질(g)":"2","지방(g)":"0.5","탄수화물(g)":"50","총당류(g)":"45","총 식이섬유(g)":"","칼슘(㎎)":"","철(㎍)":"","마그네슘(㎎)":"카페인(㎎)":""","칼륨(㎎)":"","나트륨(㎎)":"90","비타민":"","콜레스테롤(㎎)":"","총 지방산(g)":"",}</nutrition_info>
  </div_cd>
  <annotation>
    <folder>/119.상품 이미지 데이터/01.데이터/2.Validation/원천데이터/음료/10128_웅진자연은토마토500ML/</folder>
    <filename>10128_00_m_11.jpg</filename>
    <path>/119.상품 이미지 데이터/01.데이터/2.Validation/원천데이터/음료/10128_웅진자연은토마토500ML/10128_00_m_11.jpg</path>
    <source>
      <database>Unknown</database>
    </source>
    <size>
      <width>2988</width>
      <height>2988</height>
      <depth>3</depth>
    </size>
    <segmented>0</segmented>
    <object>
      <name>웅진자연은토마토500ML</name>
      <pose>Unspecified</pose>
      <truncated>0</truncated>
      <difficult>0</difficult>
      <bndbox>
        <xmin>427</xmin>
        <ymin>169</ymin>
        <xmax>1283</xmax>
        <ymax>2795</ymax>
      </bndbox>
    </object>
    <object>
      <name>웅진자연은토마토500ML</name>
      <pose>Unspecified</pose>
      <truncated>0</truncated>
      <difficult>0</difficult>
      <bndbox>
        <xmin>1731</xmin>
        <ymin>338</ymin>
        <xmax>2435</xmax>
        <ymax>2561</ymax>
      </bndbox>
    </object>
    <object>
      <name>웅진자연은토마토500ML</name>
      <pose>Unspecified</pose>
      <truncated>0</truncated>
      <difficult>0</difficult>
      <bndbox>
        <xmin>1164</xmin>
        <ymin>271</ymin>
        <xmax>1903</xmax>
        <ymax>2667</ymax>
      </bndbox>
    </object>
  </annotation>
</comp_cd>