<comp_cd>
  0775
  <identifier>
    <identifier>15119_00_m_20.jpg</identifier>
    <copyright>LOTTE Data Communication Company</copyright>
  </identifier>
  <div_cd>
    05
    <item_cd>07750700002</item_cd>
    <item_no>15119</item_no>
    <div_l>소스</div_l>
    <div_m>분말조미료</div_m>
    <div_s>후추</div_s>
    <div_n>후추</div_n>
    <comp_nm>신영</comp_nm>
    <img_prod_nm>신영 피클링스파이스 45G</img_prod_nm>
    <volume>45G</volume>
    <barcd>8809258658696</barcd>
    <width>4</width>
    <length />
    <height>11</height>
    <nutrition_info>{"1회제공량":"","총내용량(g)":"","총내용량(mL)":"","에너지(㎉)":"","단백질(g)":"","지방(g)":"","탄수화물(g)":"","총당류(g)":"","총 식이섬유(g)":"","칼슘(㎎)":"","철(㎍)":"","마그네슘(㎎)":"카페인(㎎)":""","칼륨(㎎)":"","나트륨(㎎)":"","비타민":"","콜레스테롤(㎎)":"","총 지방산(g)":"",}</nutrition_info>
  </div_cd>
  <annotation>
    <folder>/119.상품 이미지 데이터/01.데이터/2.Validation/원천데이터/소스/15119_신영피클링스파이스45G/</folder>
    <filename>15119_00_m_20.jpg</filename>
    <path>/119.상품 이미지 데이터/01.데이터/2.Validation/원천데이터/소스/15119_신영피클링스파이스45G/15119_00_m_20.jpg</path>
    <source>
      <database>Unknown</database>
    </source>
    <size>
      <width>2988</width>
      <height>2988</height>
      <depth>3</depth>
    </size>
    <segmented>0</segmented>
    <object>
      <name>신영피클링스파이스45G</name>
      <pose>Unspecified</pose>
      <truncated>0</truncated>
      <difficult>0</difficult>
      <bndbox>
        <xmin>852</xmin>
        <ymin>191</ymin>
        <xmax>1806</xmax>
        <ymax>2767</ymax>
      </bndbox>
    </object>
  </annotation>
</comp_cd>