<comp_cd>
  0101
  <identifier>
    <identifier>15724_00_m_13.jpg</identifier>
    <copyright>LOTTE Data Communication Company</copyright>
  </identifier>
  <div_cd>
    13
    <item_cd>01011300002</item_cd>
    <item_no>15724</item_no>
    <div_l>커피차</div_l>
    <div_m>분말차</div_m>
    <div_s>뿌리차</div_s>
    <div_n>뿌리차</div_n>
    <comp_nm>금광약초</comp_nm>
    <img_prod_nm>금광약초 엄나무 90G</img_prod_nm>
    <volume>90G</volume>
    <barcd>2000000123110</barcd>
    <width>11</width>
    <length>6</length>
    <height>21</height>
    <nutrition_info>{"1회제공량":"","총내용량(g)":"","총내용량(mL)":"","에너지(㎉)":"","단백질(g)":"","지방(g)":"","탄수화물(g)":"","총당류(g)":"","총 식이섬유(g)":"","칼슘(㎎)":"","철(㎍)":"","마그네슘(㎎)":"카페인(㎎)":""","칼륨(㎎)":"","나트륨(㎎)":"","비타민":"","콜레스테롤(㎎)":"","총 지방산(g)":"",}</nutrition_info>
  </div_cd>
  <annotation>
    <folder>/119.상품 이미지 데이터/01.데이터/2.Validation/원천데이터/커피차/15724_금광약초엄나무90G/</folder>
    <filename>15724_00_m_13.jpg</filename>
    <path>/119.상품 이미지 데이터/01.데이터/2.Validation/원천데이터/커피차/15724_금광약초엄나무90G/15724_00_m_13.jpg</path>
    <source>
      <database>Unknown</database>
    </source>
    <size>
      <width>2988</width>
      <height>2988</height>
      <depth>3</depth>
    </size>
    <segmented>0</segmented>
    <object>
      <name>금광약초엄나무90G</name>
      <pose>Unspecified</pose>
      <truncated>0</truncated>
      <difficult>0</difficult>
      <bndbox>
        <xmin>499</xmin>
        <ymin>542</ymin>
        <xmax>1595</xmax>
        <ymax>2364</ymax>
      </bndbox>
    </object>
    <object>
      <name>금광약초엄나무90G</name>
      <pose>Unspecified</pose>
      <truncated>0</truncated>
      <difficult>0</difficult>
      <bndbox>
        <xmin>1596</xmin>
        <ymin>559</ymin>
        <xmax>2686</xmax>
        <ymax>2392</ymax>
      </bndbox>
    </object>
  </annotation>
</comp_cd>