<comp_cd>
  0251
  <identifier>
    <identifier>20242_00_m_3.jpg</identifier>
    <copyright>LOTTE Data Communication Company</copyright>
  </identifier>
  <div_cd>
    09
    <item_cd>02510900009</item_cd>
    <item_no>20242</item_no>
    <div_l>음료</div_l>
    <div_m>과채음료</div_m>
    <div_s>과일음료</div_s>
    <div_n>과일음료</div_n>
    <comp_nm>동원F&amp;B</comp_nm>
    <img_prod_nm>동원쿨피스</img_prod_nm>
    <volume>180ML</volume>
    <barcd />
    <width>6</width>
    <length>6</length>
    <height>10</height>
    <nutrition_info>{"1회제공량":"","총내용량(g)":"","총내용량(mL)":"","에너지(㎉)":"","단백질(g)":"","지방(g)":"","탄수화물(g)":"","총당류(g)":"","총 식이섬유(g)":"","칼슘(㎎)":"","철(㎍)":"","마그네슘(㎎)":"카페인(㎎)":""","칼륨(㎎)":"","나트륨(㎎)":"","비타민":"","콜레스테롤(㎎)":"","총 지방산(g)":"",}</nutrition_info>
  </div_cd>
  <annotation>
    <folder>/119.상품 이미지 데이터/01.데이터/2.Validation/원천데이터/음료/20242_동원쿨피스/</folder>
    <filename>20242_00_m_3.jpg</filename>
    <path>/119.상품 이미지 데이터/01.데이터/2.Validation/원천데이터/음료/20242_동원쿨피스/20242_00_m_3.jpg</path>
    <source>
      <database>Unknown</database>
    </source>
    <size>
      <width>2988</width>
      <height>2988</height>
      <depth>3</depth>
    </size>
    <segmented>0</segmented>
    <object>
      <name>동원쿨피스</name>
      <pose>Unspecified</pose>
      <truncated>0</truncated>
      <difficult>0</difficult>
      <bndbox>
        <xmin>1691</xmin>
        <ymin>709</ymin>
        <xmax>2757</xmax>
        <ymax>2361</ymax>
      </bndbox>
    </object>
    <object>
      <name>동원쿨피스</name>
      <pose>Unspecified</pose>
      <truncated>0</truncated>
      <difficult>0</difficult>
      <bndbox>
        <xmin>984</xmin>
        <ymin>787</ymin>
        <xmax>1848</xmax>
        <ymax>2234</ymax>
      </bndbox>
    </object>
    <object>
      <name>동원쿨피스</name>
      <pose>Unspecified</pose>
      <truncated>0</truncated>
      <difficult>0</difficult>
      <bndbox>
        <xmin>397</xmin>
        <ymin>838</ymin>
        <xmax>1170</xmax>
        <ymax>2141</ymax>
      </bndbox>
    </object>
  </annotation>
</comp_cd>