<comp_cd>
  0825
  <identifier>
    <identifier>25482_00_m_22.jpg</identifier>
    <copyright>LOTTE Data Communication Company</copyright>
  </identifier>
  <div_cd>
    11
    <item_cd>08251100047</item_cd>
    <item_no>25482</item_no>
    <div_l>이/미용</div_l>
    <div_m>화장품</div_m>
    <div_s>리무버</div_s>
    <div_n>리무버</div_n>
    <comp_nm>아모레퍼시픽</comp_nm>
    <img_prod_nm>아모레 일리윤프레쉬모이스처 립앤아이리무버100ML</img_prod_nm>
    <volume>100ML</volume>
    <barcd>8806390541718</barcd>
    <width>4</width>
    <length />
    <height>13</height>
    <nutrition_info>{"1회제공량":"","총내용량(g)":"","총내용량(mL)":"","에너지(㎉)":"","단백질(g)":"","지방(g)":"","탄수화물(g)":"","총당류(g)":"","총 식이섬유(g)":"","칼슘(㎎)":"","철(㎍)":"","마그네슘(㎎)":"카페인(㎎)":""","칼륨(㎎)":"","나트륨(㎎)":"","비타민":"","콜레스테롤(㎎)":"","총 지방산(g)":"",}</nutrition_info>
  </div_cd>
  <annotation>
    <folder>/119.상품 이미지 데이터/01.데이터/2.Validation/원천데이터/이_미용/25482_아모레일리윤프레쉬모이스처립앤아이리무버100ML/</folder>
    <filename>25482_00_m_22.jpg</filename>
    <path>/119.상품 이미지 데이터/01.데이터/2.Validation/원천데이터/이_미용/25482_아모레일리윤프레쉬모이스처립앤아이리무버100ML/25482_00_m_22.jpg</path>
    <source>
      <database>Unknown</database>
    </source>
    <size>
      <width>2988</width>
      <height>2988</height>
      <depth>3</depth>
    </size>
    <segmented>0</segmented>
    <object>
      <name>아모레일리윤프레쉬모이스처립앤아이리무버100ML</name>
      <pose>Unspecified</pose>
      <truncated>0</truncated>
      <difficult>0</difficult>
      <bndbox>
        <xmin>819</xmin>
        <ymin>192</ymin>
        <xmax>1566</xmax>
        <ymax>2861</ymax>
      </bndbox>
    </object>
    <object>
      <name>아모레일리윤프레쉬모이스처립앤아이리무버100ML</name>
      <pose>Unspecified</pose>
      <truncated>0</truncated>
      <difficult>0</difficult>
      <bndbox>
        <xmin>1278</xmin>
        <ymin>257</ymin>
        <xmax>2050</xmax>
        <ymax>2717</ymax>
      </bndbox>
    </object>
  </annotation>
</comp_cd>