<comp_cd>
  0306
  <identifier>
    <identifier>45670_00_m_6.jpg</identifier>
    <copyright>LOTTE Data Communication Company</copyright>
  </identifier>
  <div_cd>
    13
    <item_cd>03061300003</item_cd>
    <item_no>45670</item_no>
    <div_l>커피차</div_l>
    <div_m>분말차</div_m>
    <div_s>커피</div_s>
    <div_n>아메리카노</div_n>
    <comp_nm>롯데푸드</comp_nm>
    <img_prod_nm>롯데푸드)콜롬비아유기농</img_prod_nm>
    <volume>40G</volume>
    <barcd>8801056056469</barcd>
    <width>9</width>
    <length>7</length>
    <height>11</height>
    <nutrition_info>{"1회제공량":"","총내용량(g)":"","총내용량(mL)":"","에너지(㎉)":"","단백질(g)":"","지방(g)":"","탄수화물(g)":"","총당류(g)":"","총 식이섬유(g)":"","칼슘(㎎)":"","철(㎍)":"","마그네슘(㎎)":"카페인(㎎)":""","칼륨(㎎)":"","나트륨(㎎)":"","비타민":"","콜레스테롤(㎎)":"","총 지방산(g)":"",}</nutrition_info>
  </div_cd>
  <annotation>
    <folder>/119.상품 이미지 데이터/01.데이터/2.Validation/원천데이터/커피차/45670_롯데푸드)콜롬비아유기농/</folder>
    <filename>45670_00_m_6.jpg</filename>
    <path>/119.상품 이미지 데이터/01.데이터/2.Validation/원천데이터/커피차/45670_롯데푸드)콜롬비아유기농/45670_00_m_6.jpg</path>
    <source>
      <database>Unknown</database>
    </source>
    <size>
      <width>2988</width>
      <height>2988</height>
      <depth>3</depth>
    </size>
    <segmented>0</segmented>
    <object>
      <name>롯데푸드)콜롬비아유기농</name>
      <pose>Unspecified</pose>
      <truncated>0</truncated>
      <difficult>0</difficult>
      <bndbox>
        <xmin>1056</xmin>
        <ymin>506</ymin>
        <xmax>2501</xmax>
        <ymax>2579</ymax>
      </bndbox>
    </object>
  </annotation>
</comp_cd>