<comp_cd>
  0722
  <identifier>
    <identifier>45862_00_m_14.jpg</identifier>
    <copyright>LOTTE Data Communication Company</copyright>
  </identifier>
  <div_cd>
    01
    <item_cd>07220100005</item_cd>
    <item_no>45862</item_no>
    <div_l>과자</div_l>
    <div_m>초콜렛</div_m>
    <div_s>바초콜릿</div_s>
    <div_n>바초콜릿</div_n>
    <comp_nm>스위트스페이스</comp_nm>
    <img_prod_nm>스위트스페이스)팀탐츄이카라멜</img_prod_nm>
    <volume>175G</volume>
    <barcd>9310072001210</barcd>
    <width>23</width>
    <length>5</length>
    <height>7</height>
    <nutrition_info>{"1회제공량":"175","총내용량(g)":"175","총내용량(mL)":"0","에너지(㎉)":"858","단백질(g)":"8.1","지방(g)":"41.5","탄수화물(g)":"113.1","총당류(g)":"80","총 식이섬유(g)":"0","칼슘(㎎)":"0","철(㎍)":"0","마그네슘(㎎)":"카페인(㎎)":"0"0","칼륨(㎎)":"0","나트륨(㎎)":"190.5","비타민":"0","콜레스테롤(㎎)":"0","총 지방산(g)":"0",}</nutrition_info>
  </div_cd>
  <annotation>
    <folder>/119.상품 이미지 데이터/01.데이터/2.Validation/원천데이터/과자/45862_스위트스페이스)팀탐츄이카라멜/</folder>
    <filename>45862_00_m_14.jpg</filename>
    <path>/119.상품 이미지 데이터/01.데이터/2.Validation/원천데이터/과자/45862_스위트스페이스)팀탐츄이카라멜/45862_00_m_14.jpg</path>
    <source>
      <database>Unknown</database>
    </source>
    <size>
      <width>2988</width>
      <height>2988</height>
      <depth>3</depth>
    </size>
    <segmented>0</segmented>
    <object>
      <name>스위트스페이스)팀탐츄이카라멜</name>
      <pose>Unspecified</pose>
      <truncated>0</truncated>
      <difficult>0</difficult>
      <bndbox>
        <xmin>238</xmin>
        <ymin>1434</ymin>
        <xmax>1755</xmax>
        <ymax>1982</ymax>
      </bndbox>
    </object>
  </annotation>
</comp_cd>