<comp_cd>
  0975
  <identifier>
    <identifier>65423_00_m_17.jpg</identifier>
    <copyright>LOTTE Data Communication Company</copyright>
  </identifier>
  <div_cd>
    05
    <item_cd>09750500102</item_cd>
    <item_no>65423</item_no>
    <div_l>상온HMR</div_l>
    <div_m>레토르트</div_m>
    <div_s>즉석밥</div_s>
    <div_n>즉석밥</div_n>
    <comp_nm>오뚜기</comp_nm>
    <img_prod_nm>오뚜기맛있는오뚜기뚝배기불고기밥</img_prod_nm>
    <volume>320G</volume>
    <barcd>8801045892320</barcd>
    <width>10</width>
    <length>10</length>
    <height>11</height>
    <nutrition_info>{"1회제공량":"320","총내용량(g)":"320","총내용량(mL)":"","에너지(㎉)":"365","단백질(g)":"11","지방(g)":"2.3","탄수화물(g)":"75","총당류(g)":"8","총 식이섬유(g)":"","칼슘(㎎)":"","철(㎍)":"","마그네슘(㎎)":"카페인(㎎)":""","칼륨(㎎)":"","나트륨(㎎)":"990","비타민":"","콜레스테롤(㎎)":"15","총 지방산(g)":"2.3",}</nutrition_info>
  </div_cd>
  <annotation>
    <folder>/119.상품 이미지 데이터/01.데이터/2.Validation/원천데이터/상온HMR/65423_오뚜기맛있는오뚜기뚝배기불고기밥/</folder>
    <filename>65423_00_m_17.jpg</filename>
    <path>/119.상품 이미지 데이터/01.데이터/2.Validation/원천데이터/상온HMR/65423_오뚜기맛있는오뚜기뚝배기불고기밥/65423_00_m_17.jpg</path>
    <source>
      <database>Unknown</database>
    </source>
    <size>
      <width>2988</width>
      <height>2988</height>
      <depth>3</depth>
    </size>
    <segmented>0</segmented>
    <object>
      <name>오뚜기맛있는오뚜기뚝배기불고기밥</name>
      <pose>Unspecified</pose>
      <truncated>0</truncated>
      <difficult>0</difficult>
      <bndbox>
        <xmin>998</xmin>
        <ymin>940</ymin>
        <xmax>2529</xmax>
        <ymax>2141</ymax>
      </bndbox>
    </object>
    <object>
      <name>오뚜기맛있는오뚜기뚝배기불고기밥</name>
      <pose>Unspecified</pose>
      <truncated>0</truncated>
      <difficult>0</difficult>
      <bndbox>
        <xmin>584</xmin>
        <ymin>1120</ymin>
        <xmax>1609</xmax>
        <ymax>1976</ymax>
      </bndbox>
    </object>
  </annotation>
</comp_cd>