<comp_cd>
  1062
  <identifier>
    <identifier>65916_00_m_15.jpg</identifier>
    <copyright>LOTTE Data Communication Company</copyright>
  </identifier>
  <div_cd>
    01
    <item_cd>10620100001</item_cd>
    <item_no>65916</item_no>
    <div_l>과자</div_l>
    <div_m>초콜렛</div_m>
    <div_s>쉘초콜릿</div_s>
    <div_n>쉘초콜릿</div_n>
    <comp_nm>유한회사아이디어원</comp_nm>
    <img_prod_nm>유한회사아이디어원)쥐방울멜티키스밀크초코볼</img_prod_nm>
    <volume>145G</volume>
    <barcd>6928115019257</barcd>
    <width>12</width>
    <length>6</length>
    <height>19</height>
    <nutrition_info>{"1회제공량":"100","총내용량(g)":"145","총내용량(mL)":"0","에너지(㎉)":"540","단백질(g)":"7.4","지방(g)":"30.8","탄수화물(g)":"58.9","총당류(g)":"58.9","총 식이섬유(g)":"0","칼슘(㎎)":"0","철(㎍)":"0","마그네슘(㎎)":"카페인(㎎)":"0"0","칼륨(㎎)":"0","나트륨(㎎)":"102","비타민":"0","콜레스테롤(㎎)":"0","총 지방산(g)":"0",}</nutrition_info>
  </div_cd>
  <annotation>
    <folder>/119.상품 이미지 데이터/01.데이터/2.Validation/원천데이터/과자/65916_유한회사아이디어원)쥐방울멜티키스밀크초코볼/</folder>
    <filename>65916_00_m_15.jpg</filename>
    <path>/119.상품 이미지 데이터/01.데이터/2.Validation/원천데이터/과자/65916_유한회사아이디어원)쥐방울멜티키스밀크초코볼/65916_00_m_15.jpg</path>
    <source>
      <database>Unknown</database>
    </source>
    <size>
      <width>2988</width>
      <height>2988</height>
      <depth>3</depth>
    </size>
    <segmented>0</segmented>
    <object>
      <name>유한회사아이디어원)쥐방울멜티키스밀크초코볼</name>
      <pose>Unspecified</pose>
      <truncated>0</truncated>
      <difficult>0</difficult>
      <bndbox>
        <xmin>1517</xmin>
        <ymin>450</ymin>
        <xmax>2812</xmax>
        <ymax>2455</ymax>
      </bndbox>
    </object>
    <object>
      <name>유한회사아이디어원)쥐방울멜티키스밀크초코볼</name>
      <pose>Unspecified</pose>
      <truncated>0</truncated>
      <difficult>0</difficult>
      <bndbox>
        <xmin>545</xmin>
        <ymin>635</ymin>
        <xmax>1592</xmax>
        <ymax>2315</ymax>
      </bndbox>
    </object>
  </annotation>
</comp_cd>