<comp_cd>
  1347
  <identifier>
    <identifier>66014_00_m_14.jpg</identifier>
    <copyright>LOTTE Data Communication Company</copyright>
  </identifier>
  <div_cd>
    13
    <item_cd>13471300007</item_cd>
    <item_no>66014</item_no>
    <div_l>커피차</div_l>
    <div_m>분말차</div_m>
    <div_s>잎차</div_s>
    <div_n>보이차</div_n>
    <comp_nm>티젠</comp_nm>
    <img_prod_nm>티젠)티젠보이차10T마실수록가벼워지는보이차</img_prod_nm>
    <volume>18G</volume>
    <barcd>8809071544534</barcd>
    <width>9</width>
    <length>4</length>
    <height>14</height>
    <nutrition_info>{"1회제공량":"1.8","총내용량(g)":"18","총내용량(mL)":"","에너지(㎉)":"4.5","단백질(g)":"","지방(g)":"","탄수화물(g)":"1","총당류(g)":"","총 식이섬유(g)":"0.7","칼슘(㎎)":"","철(㎍)":"","마그네슘(㎎)":"카페인(㎎)":""","칼륨(㎎)":"","나트륨(㎎)":"","비타민":"","콜레스테롤(㎎)":"","총 지방산(g)":"",}</nutrition_info>
  </div_cd>
  <annotation>
    <folder>/119.상품 이미지 데이터/01.데이터/2.Validation/원천데이터/커피차/66014_티젠)티젠보이차10T마실수록가벼워지는보이차/</folder>
    <filename>66014_00_m_14.jpg</filename>
    <path>/119.상품 이미지 데이터/01.데이터/2.Validation/원천데이터/커피차/66014_티젠)티젠보이차10T마실수록가벼워지는보이차/66014_00_m_14.jpg</path>
    <source>
      <database>Unknown</database>
    </source>
    <size>
      <width>2988</width>
      <height>2988</height>
      <depth>3</depth>
    </size>
    <segmented>0</segmented>
    <object>
      <name>티젠)티젠보이차10T마실수록가벼워지는보이차</name>
      <pose>Unspecified</pose>
      <truncated>0</truncated>
      <difficult>0</difficult>
      <bndbox>
        <xmin>322</xmin>
        <ymin>371</ymin>
        <xmax>1577</xmax>
        <ymax>2424</ymax>
      </bndbox>
    </object>
    <object>
      <name>티젠)티젠보이차10T마실수록가벼워지는보이차</name>
      <pose>Unspecified</pose>
      <truncated>0</truncated>
      <difficult>0</difficult>
      <bndbox>
        <xmin>1441</xmin>
        <ymin>301</ymin>
        <xmax>2747</xmax>
        <ymax>2557</ymax>
      </bndbox>
    </object>
  </annotation>
</comp_cd>