<comp_cd>
  0305
  <identifier>
    <identifier>80045_0_m_12.jpg</identifier>
    <copyright>LOTTE Data Communication Company</copyright>
  </identifier>
  <div_cd>
    09
    <item_cd>03050900192</item_cd>
    <item_no>80045</item_no>
    <div_l>음료</div_l>
    <div_m>탄산음료</div_m>
    <div_s>혼합탄산</div_s>
    <div_n>혼합탄산</div_n>
    <comp_nm>롯데칠성음료</comp_nm>
    <img_prod_nm>롯데트로피카나스파클링복숭아400ML</img_prod_nm>
    <volume>400ML</volume>
    <barcd />
    <width>6</width>
    <length />
    <height>22</height>
    <nutrition_info>{"1회제공량":"400","총내용량(g)":"0","총내용량(mL)":"400","에너지(㎉)":"230","단백질(g)":"","지방(g)":"0","탄수화물(g)":"57","총당류(g)":"57","총 식이섬유(g)":"0","칼슘(㎎)":"0","철(㎍)":"0","마그네슘(㎎)":"카페인(㎎)":""0","칼륨(㎎)":"0","나트륨(㎎)":"31","비타민":"","콜레스테롤(㎎)":"","총 지방산(g)":"",}</nutrition_info>
  </div_cd>
  <annotation>
    <folder>/119.상품 이미지 데이터/01.데이터/2.Validation/원천데이터/음료/80045_롯데트로피카나스파클링복숭아400ML/</folder>
    <filename>80045_0_m_12.jpg</filename>
    <path>/119.상품 이미지 데이터/01.데이터/2.Validation/원천데이터/음료/80045_롯데트로피카나스파클링복숭아400ML/80045_0_m_12.jpg</path>
    <source>
      <database>Unknown</database>
    </source>
    <size>
      <width>2988</width>
      <height>2988</height>
      <depth>3</depth>
    </size>
    <segmented>0</segmented>
    <object>
      <name>롯데트로피카나스파클링복숭아400ML</name>
      <pose>Unspecified</pose>
      <truncated>0</truncated>
      <difficult>0</difficult>
      <bndbox>
        <xmin>549</xmin>
        <ymin>335</ymin>
        <xmax>1217</xmax>
        <ymax>2764</ymax>
      </bndbox>
    </object>
    <object>
      <name>롯데트로피카나스파클링복숭아400ML</name>
      <pose>Unspecified</pose>
      <truncated>0</truncated>
      <difficult>0</difficult>
      <bndbox>
        <xmin>1819</xmin>
        <ymin>402</ymin>
        <xmax>2460</xmax>
        <ymax>2675</ymax>
      </bndbox>
    </object>
    <object>
      <name>롯데트로피카나스파클링복숭아400ML</name>
      <pose>Unspecified</pose>
      <truncated>0</truncated>
      <difficult>0</difficult>
      <bndbox>
        <xmin>1202</xmin>
        <ymin>371</ymin>
        <xmax>1846</xmax>
        <ymax>2719</ymax>
      </bndbox>
    </object>
  </annotation>
</comp_cd>