<comp_cd>
  0509
  <identifier>
    <identifier>85005_00_m_14.jpg</identifier>
    <copyright>LOTTE Data Communication Company</copyright>
  </identifier>
  <div_cd>
    05
    <item_cd>05090500007</item_cd>
    <item_no>85005</item_no>
    <div_l>상온HMR</div_l>
    <div_m>가공분말류</div_m>
    <div_s>기타프리믹스</div_s>
    <div_n>기타프리믹스</div_n>
    <comp_nm>브레드가</comp_nm>
    <img_prod_nm>브레드가든피코크핑크퐁베이킹믹스초코칩쿠키만들기</img_prod_nm>
    <volume>265G</volume>
    <barcd>8809015182785</barcd>
    <width>11</width>
    <length>5</length>
    <height>21</height>
    <nutrition_info>{"1회제공량":"265","총내용량(g)":"265","총내용량(mL)":"","에너지(㎉)":"1060","단백질(g)":"18","지방(g)":"16","탄수화물(g)":"212","총당류(g)":"124","총 식이섬유(g)":"","칼슘(㎎)":"","철(㎍)":"","마그네슘(㎎)":"카페인(㎎)":""","칼륨(㎎)":"","나트륨(㎎)":"759","비타민":"","콜레스테롤(㎎)":"0","총 지방산(g)":"16",}</nutrition_info>
  </div_cd>
  <annotation>
    <folder>/119.상품 이미지 데이터/01.데이터/2.Validation/원천데이터/상온HMR/85005_브레드가든피코크핑크퐁베이킹믹스초코칩쿠키만들기/</folder>
    <filename>85005_00_m_14.jpg</filename>
    <path>/119.상품 이미지 데이터/01.데이터/2.Validation/원천데이터/상온HMR/85005_브레드가든피코크핑크퐁베이킹믹스초코칩쿠키만들기/85005_00_m_14.jpg</path>
    <source>
      <database>Unknown</database>
    </source>
    <size>
      <width>2988</width>
      <height>2988</height>
      <depth>3</depth>
    </size>
    <segmented>0</segmented>
    <object>
      <name>브레드가든피코크핑크퐁베이킹믹스초코칩쿠키만들기</name>
      <pose>Unspecified</pose>
      <truncated>0</truncated>
      <difficult>0</difficult>
      <bndbox>
        <xmin>1377</xmin>
        <ymin>339</ymin>
        <xmax>2519</xmax>
        <ymax>2553</ymax>
      </bndbox>
    </object>
    <object>
      <name>브레드가든피코크핑크퐁베이킹믹스초코칩쿠키만들기</name>
      <pose>Unspecified</pose>
      <truncated>0</truncated>
      <difficult>0</difficult>
      <bndbox>
        <xmin>423</xmin>
        <ymin>421</ymin>
        <xmax>1407</xmax>
        <ymax>2475</ymax>
      </bndbox>
    </object>
  </annotation>
</comp_cd>